pyransac3d/__init__.py
pyransac3d/aux_functions.py
pyransac3d/circle.py
pyransac3d/cuboid.py
pyransac3d/cylinder.py
pyransac3d/line.py
pyransac3d/plane.py
pyransac3d/point.py
pyransac3d/sphere.py
pyransac3d-0.6.0.dist-info/LICENSE
pyransac3d-0.6.0.dist-info/METADATA
pyransac3d-0.6.0.dist-info/WHEEL
pyransac3d-0.6.0.dist-info/top_level.txt
pyransac3d-0.6.0.dist-info/RECORD
