Metadata-Version: 2.1
Name: pyransac3d
Version: 0.6.0
Summary: A python tool for fitting primitives 3D shapes in point clouds using RANSAC algorithm 
Home-page: https://github.com/leomariga/pyRANSAC-3D
Author: Leonardo Mariga
Author-email: leomariga@gmail.com
License: UNKNOWN
Project-URL: Documentation, https://leomariga.github.io/pyRANSAC-3D/
Project-URL: Source, https://github.com/leomariga/pyRANSAC-3D
Keywords: point-cloud,segmentation,ransac,cuboid,3d-reconstruction,cylinder,planes,open3d,plane-detection,ransac-algorithm
Platform: UNKNOWN
Classifier: Programming Language :: Python :: 3
Classifier: License :: OSI Approved :: Apache Software License
Classifier: Operating System :: OS Independent
Requires-Python: >=3.6
